moose/model_utils.py
moose/_moose.cpython-314-darwin.so
moose/moose_constants.py
moose/server.py
moose/methods_utils.py
moose/fixXreacs.py
moose/optimizer_interface.py
moose/recording.py
moose/print_utils.py
moose/constants.py
moose/__init__.py
moose/hdfutil.py
moose/moose_legacy.py
moose/utils.py
moose/plot_utils.py
moose/helper.py
moose/tests.py
moose/streamer_utils.py
moose/network_utils.py
moose/neuroml2/test_reader.py
moose/neuroml2/units.py
moose/neuroml2/hhfit.py
moose/neuroml2/test_reader2.py
moose/neuroml2/test_reader3.py
moose/neuroml2/__init__.py
moose/neuroml2/run_hhcell.py
moose/neuroml2/README
moose/neuroml2/reader.py
moose/neuroml2/run_cell.py
moose/neuroml2/test_reader4.py
moose/neuroml2/test_granule98.py
moose/neuroml2/schema/NeuroMLCoreDimensions.xml
moose/neuroml2/test_files/passiveCell.nml
moose/neuroml2/test_files/Purk2M9s.nml
moose/neuroml2/test_files/LEMS_passiveCell.xml
moose/neuroml2/test_files/NML2_FullCell.nml
moose/neuroml2/test_files/SimpleIonChannel.xml
moose/neuroml2/test_files/LEMS_hhCell.xml
moose/neuroml2/test_files/NML2_SingleCompHHCell.nml
moose/neuroml/ChannelML.py
moose/neuroml/MorphML.py
moose/neuroml/__init__.py
moose/neuroml/NeuroML.py
moose/neuroml/utils.py
moose/neuroml/NetworkML.py
moose/.dylibs/libhdf5.310.5.1.dylib
moose/.dylibs/libaec.0.1.4.dylib
moose/.dylibs/libgsl.28.dylib
moose/.dylibs/libsz.2.0.1.dylib
moose/.dylibs/libhdf5_hl.310.0.6.dylib
moose/SBML/writeSBML.py
moose/SBML/__init__.py
moose/SBML/readSBML.py
moose/SBML/validation.py
moose/genesis/__init__.py
moose/genesis/writeKkit.py
moose/chemMerge/merge.py
moose/chemMerge/__init__.py
moose/chemMerge/mtypes.py
moose/chemUtil/add_Delete_ChemicalSolver.py
moose/chemUtil/rainbow2.pkl
moose/chemUtil/__init__.py
moose/chemUtil/graphUtils.py
moose/chemUtil/chemConnectUtil.py
pymoose-4.1.4.dist-info/RECORD
pymoose-4.1.4.dist-info/LICENSE
pymoose-4.1.4.dist-info/WHEEL
pymoose-4.1.4.dist-info/METADATA
rdesigneur/jardesigner.py
rdesigneur/nsdfview.py
rdesigneur/rdesigneur.py
rdesigneur/moogul.py
rdesigneur/__init__.py
