Metadata-Version: 2.1
Name: pymoose
Version: 4.1.4
Summary: Python scripting interface of MOOSE Simulator (https://moose.ncbs.res.in)
Author: Niraj Dudani, Aditya Gilra, Aviral Goel, Dilawar Singh, Dharma Teja, Malav Shah, Dhruva Gowda
Author-Email: "Upinder S. Bhalla" <bhalla@ncbs.res.in>, Subhasis Ray <ray.subhasis@gmail.com>, "G.V. Harsharani" <hrani@ncbs.res.in>
Maintainer-Email: "Upinder S. Bhalla" <bhalla@ncbs.res.in>, Subhasis Ray <ray.subhasis@gmail.com>, "G.V. Harsharani" <hrani@ncbs.res.in>
License:                     GNU GENERAL PUBLIC LICENSE
Classifier: Development Status :: 5 - Production/Stable
Classifier: Intended Audience :: Science/Research
Classifier: Intended Audience :: Developers
Classifier: License :: OSI Approved :: GNU General Public License v3 (GPLv3)
Classifier: Programming Language :: C
Classifier: Programming Language :: C++
Classifier: Programming Language :: Python
Classifier: Programming Language :: Python :: 3
Classifier: Programming Language :: Python :: 3.8
Classifier: Programming Language :: Python :: 3.9
Classifier: Programming Language :: Python :: 3.10
Classifier: Programming Language :: Python :: 3.11
Classifier: Programming Language :: Python :: 3.12
Classifier: Programming Language :: Python :: 3.13
Classifier: Programming Language :: Python :: 3.14
Classifier: Topic :: Software Development :: Libraries
Classifier: Topic :: Scientific/Engineering
Classifier: Operating System :: Microsoft :: Windows
Classifier: Operating System :: POSIX :: Linux
Classifier: Operating System :: POSIX
Classifier: Operating System :: Unix
Classifier: Operating System :: MacOS
Project-URL: homepage, https://mooseneuro.github.io/
Project-URL: documentation, https://moose.ncbs.res.in/readthedocs/index.html
Project-URL: repository, https://github.com/MooseNeuro/moose-core.git
Requires-Python: >=3.8
Requires-Dist: numpy>=1.23
Requires-Dist: matplotlib
Requires-Dist: vpython
Requires-Dist: python-libsbml
Requires-Dist: pyneuroml
Provides-Extra: test
Requires-Dist: coverage; extra == "test"
Requires-Dist: pytest; extra == "test"
Requires-Dist: pytest-cov; extra == "test"
